django_sqids/__init__.py
django_sqids/exceptions.py
django_sqids/field.py
django_sqids-0.2.2.dist-info/LICENSE
django_sqids-0.2.2.dist-info/METADATA
django_sqids-0.2.2.dist-info/WHEEL
django_sqids-0.2.2.dist-info/RECORD
