Metadata-Version: 2.3
Name: django-sqids
Version: 0.2.2
Summary: Non-intrusive sqids library for Django
License: MIT
Keywords: django,sqids,sqid,hashids,hashid
Author: Julian Wachholz
Author-email: julian@wachholz.ch
Requires-Python: >=3.8.1,<4
Classifier: License :: OSI Approved :: MIT License
Classifier: Programming Language :: Python :: 3
Classifier: Programming Language :: Python :: 3.9
Classifier: Programming Language :: Python :: 3.10
Classifier: Programming Language :: Python :: 3.11
Classifier: Programming Language :: Python :: 3.12
Classifier: Programming Language :: Python :: 3.13
Requires-Dist: sqids (>=0.4.1)
Project-URL: Homepage, https://github.com/julianwachholz/django-sqids
Project-URL: Repository, https://github.com/julianwachholz/django-sqids
